pyfakers/_native__lib.cpython-36m-x86_64-linux-gnu.so
pyfakers/__init__.py
pyfakers/_native.py
pyfakers/_native__lib.so
pyfakers/_native__ffi.py
pyfakers-0.1.0.dist-info/metadata.json
pyfakers-0.1.0.dist-info/RECORD
pyfakers-0.1.0.dist-info/METADATA
pyfakers-0.1.0.dist-info/WHEEL
pyfakers-0.1.0.dist-info/DESCRIPTION.rst
pyfakers-0.1.0.dist-info/top_level.txt
