Metadata-Version: 2.0
Name: pyfakers
Version: 0.1.0
Summary: A fake data generator backed by fake-rs
Home-page: UNKNOWN
Author: UNKNOWN
Author-email: UNKNOWN
License: UNKNOWN
Platform: any
Requires-Dist: wheel
Requires-Dist: milksnake
Requires-Dist: pipenv
Requires-Dist: pytest
